bobbin/__init__.py
bobbin/array_util.py
bobbin/cron.py
bobbin/evaluation.py
bobbin/pmap_util.py
bobbin/pytypes.py
bobbin/tensorboard.py
bobbin/training.py
bobbin/var_util.py
bobbin/example_lib/asrio.py
bobbin/example_lib/asrnn.py
devenv/bin/rst2html.py
devenv/bin/rst2html4.py
devenv/bin/rst2html5.py
devenv/bin/rst2latex.py
devenv/bin/rst2man.py
devenv/bin/rst2odt.py
devenv/bin/rst2odt_prepstyles.py
devenv/bin/rst2pseudoxml.py
devenv/bin/rst2s5.py
devenv/bin/rst2xetex.py
devenv/bin/rst2xml.py
devenv/bin/rstpep2html.py
docs/conf.py
docs/_build/jupyter_execute/pmap_util.py
docs/_build/jupyter_execute/var_util.py
examples/mnist.py
examples/librispeech/data_bench.py
examples/librispeech/prepare_normalizer.py
examples/librispeech/train.py
tests/array_util_test.py
tests/cron_test.py
tests/evaluation_test.py
tests/example_test.py
tests/pmap_util_test.py
tests/tensorboard_test.py
tests/training_test.py
tests/var_util_test.py
tests/example_lib/asrio_test.py
tests/example_lib/asrnn_test.py
bobbin-0.0.2.dist-info/LICENSE
bobbin-0.0.2.dist-info/METADATA
bobbin-0.0.2.dist-info/WHEEL
bobbin-0.0.2.dist-info/top_level.txt
bobbin-0.0.2.dist-info/RECORD
