Metadata-Version: 2.1
Name: bobbin
Version: 0.0.2
Summary: Tools for making training loops with flax.linen models.
Home-page: https://github.com/yotarok/bobbin
Author: Bobbin Team
Author-email: yotaro@google.com
Keywords: python machine learning flax
Classifier: Development Status :: 1 - Planning
Classifier: Environment :: Console
Classifier: Intended Audience :: Science/Research
Classifier: Intended Audience :: Developers
Classifier: License :: OSI Approved :: Apache Software License
Classifier: Operating System :: OS Independent
Classifier: Programming Language :: Python
Classifier: Programming Language :: Python :: 3
Classifier: Topic :: Scientific/Engineering :: Artificial Intelligence
Classifier: Topic :: Software Development :: Libraries :: Python Modules
Requires-Python: >=3.8
License-File: LICENSE
Requires-Dist: etils
Requires-Dist: flax (>=0.6.3)
Requires-Dist: jax (>=0.3.16)
Requires-Dist: matplotlib
Requires-Dist: numpy (>=1.18.0)
Requires-Dist: tensorflow
